[{"id":"AF","value":"Afghanistan"},{"id":"ZA","value":"Africa dal Sid"},{"id":"AL","value":"Albania"},{"id":"DZ","value":"Algeria"},{"id":"AD","value":"Andorra"},{"id":"AO","value":"Angola"},{"id":"AI","value":"Anguilla"},{"id":"AQ","value":"Antarctica"},{"id":"AG","value":"Antigua e Barbuda"},{"id":"SA","value":"Arabia Saudita"},{"id":"AR","value":"Argentinia"},{"id":"AM","value":"Armenia"},{"id":"AW","value":"Aruba"},{"id":"AC","value":"Ascension Island"},{"id":"AZ","value":"Aserbaidschan"},{"id":"AU","value":"Australia"},{"id":"AT","value":"Austria"},{"id":"BS","value":"Bahamas"},{"id":"BH","value":"Bahrain"},{"id":"BD","value":"Bangladesch"},{"id":"BB","value":"Barbados"},{"id":"BE","value":"Belgia"},{"id":"BZ","value":"Belize"},{"id":"BJ","value":"Benin"},{"id":"BM","value":"Bermudas"},{"id":"BT","value":"Bhutan"},{"id":"BY","value":"Bielorussia"},{"id":"BO","value":"Bolivia"},{"id":"BA","value":"Bosnia ed Erzegovina"},{"id":"BW","value":"Botswana"},{"id":"BR","value":"Brasila"},{"id":"BN","value":"Brunei"},{"id":"BG","value":"Bulgaria"},{"id":"BF","value":"Burkina Faso"},{"id":"BI","value":"Burundi"},{"id":"KH","value":"Cambodscha"},{"id":"CM","value":"Camerun"},{"id":"CA","value":"Canada"},{"id":"IC","value":"Canary Islands"},{"id":"CV","value":"Cap Verd"},{"id":"BQ","value":"Caribbean Netherlands"},{"id":"EA","value":"Ceuta & Melilla"},{"id":"CL","value":"Chile"},{"id":"CN","value":"China"},{"id":"CY","value":"Cipra"},{"id":"VA","value":"Citad dal Vatican"},{"id":"CO","value":"Columbia"},{"id":"KM","value":"Comoras"},{"id":"CG","value":"Congo"},{"id":"KP","value":"Corea dal Nord"},{"id":"KR","value":"Corea dal Sid"},{"id":"CI","value":"Costa d\u2019Ivur"},{"id":"CR","value":"Costa Rica"},{"id":"HR","value":"Croazia"},{"id":"CU","value":"Cuba"},{"id":"CW","value":"Cura\u00e7ao"},{"id":"DK","value":"Danemarc"},{"id":"DG","value":"Diego Garcia"},{"id":"DM","value":"Dominica"},{"id":"DJ","value":"Dschibuti"},{"id":"EC","value":"Ecuador"},{"id":"EG","value":"Egipta"},{"id":"SV","value":"El Salvador"},{"id":"AE","value":"Emirats Arabs Unids"},{"id":"ER","value":"Eritrea"},{"id":"EE","value":"Estonia"},{"id":"ET","value":"Etiopia"},{"id":"FJ","value":"Fidschi"},{"id":"PH","value":"Filippinas"},{"id":"FI","value":"Finlanda"},{"id":"FR","value":"Frantscha"},{"id":"GA","value":"Gabun"},{"id":"GM","value":"Gambia"},{"id":"GE","value":"Georgia"},{"id":"GS","value":"Georgia dal Sid e las Inslas Sandwich dal Sid"},{"id":"DE","value":"Germania"},{"id":"GH","value":"Ghana"},{"id":"JM","value":"Giamaica"},{"id":"JP","value":"Giapun"},{"id":"GI","value":"Gibraltar"},{"id":"GD","value":"Grenada"},{"id":"GR","value":"Grezia"},{"id":"GL","value":"Gr\u00f6nlanda"},{"id":"GP","value":"Guadeloupe"},{"id":"GU","value":"Guam"},{"id":"GT","value":"Guatemala"},{"id":"GG","value":"Guernsey"},{"id":"GN","value":"Guinea"},{"id":"GQ","value":"Guinea Equatoriala"},{"id":"GW","value":"Guinea-Bissau"},{"id":"GY","value":"Guyana"},{"id":"GF","value":"Guyana Franzosa"},{"id":"HT","value":"Haiti"},{"id":"HN","value":"Honduras"},{"id":"IN","value":"India"},{"id":"ID","value":"Indonesia"},{"id":"CX","value":"Insla da Christmas"},{"id":"IM","value":"Insla da Man"},{"id":"NF","value":"Insla Norfolk"},{"id":"AX","value":"Inslas Aland"},{"id":"KY","value":"Inslas Cayman"},{"id":"CC","value":"Inslas Cocos"},{"id":"CK","value":"Inslas Cook"},{"id":"MH","value":"Inslas da Marshall"},{"id":"FK","value":"Inslas dal Falkland"},{"id":"FO","value":"Inslas Feroe"},{"id":"MP","value":"Inslas Mariannas dal Nord"},{"id":"UM","value":"Inslas pitschnas perifericas dals Stadis Unids da l\u2019America"},{"id":"TC","value":"Inslas Turks e Caicos"},{"id":"VI","value":"Inslas Verginas Americanas"},{"id":"VG","value":"Inslas Verginas Britannicas"},{"id":"IQ","value":"Irac"},{"id":"IR","value":"Iran"},{"id":"IE","value":"Irlanda"},{"id":"IS","value":"Islanda"},{"id":"IL","value":"Israel"},{"id":"IT","value":"Italia"},{"id":"YE","value":"Jemen"},{"id":"JE","value":"Jersey"},{"id":"JO","value":"Jordania"},{"id":"KZ","value":"Kasachstan"},{"id":"QA","value":"Katar"},{"id":"KE","value":"Kenia"},{"id":"KG","value":"Kirghisistan"},{"id":"KI","value":"Kiribati"},{"id":"XK","value":"Kosovo"},{"id":"KW","value":"Kuwait"},{"id":"LA","value":"Laos"},{"id":"LS","value":"Lesotho"},{"id":"LV","value":"Lettonia"},{"id":"LB","value":"Libanon"},{"id":"LR","value":"Liberia"},{"id":"LY","value":"Libia"},{"id":"LI","value":"Liechtenstein"},{"id":"LT","value":"Lituania"},{"id":"LU","value":"Luxemburg"},{"id":"MK","value":"Macedonia"},{"id":"MG","value":"Madagascar"},{"id":"MY","value":"Malaisia"},{"id":"MW","value":"Malawi"},{"id":"MV","value":"Maldivas"},{"id":"ML","value":"Mali"},{"id":"MT","value":"Malta"},{"id":"MA","value":"Maroc"},{"id":"MQ","value":"Martinique"},{"id":"MR","value":"Mauretania"},{"id":"MU","value":"Mauritius"},{"id":"YT","value":"Mayotte"},{"id":"MX","value":"Mexico"},{"id":"FM","value":"Micronesia"},{"id":"MD","value":"Moldavia"},{"id":"MC","value":"Monaco"},{"id":"MN","value":"Mongolia"},{"id":"ME","value":"Montenegro"},{"id":"MS","value":"Montserrat"},{"id":"MZ","value":"Mosambic"},{"id":"MM","value":"Myanmar"},{"id":"NA","value":"Namibia"},{"id":"NR","value":"Nauru"},{"id":"NP","value":"Nepal"},{"id":"NI","value":"Nicaragua"},{"id":"NE","value":"Niger"},{"id":"NG","value":"Nigeria"},{"id":"NU","value":"Niue"},{"id":"NO","value":"Norvegia"},{"id":"NC","value":"Nova Caledonia"},{"id":"NZ","value":"Nova Zelanda"},{"id":"OM","value":"Oman"},{"id":"NL","value":"Pajais Bass"},{"id":"PK","value":"Pakistan"},{"id":"PW","value":"Palau"},{"id":"PA","value":"Panama"},{"id":"PG","value":"Papua Nova Guinea"},{"id":"PY","value":"Paraguai"},{"id":"PE","value":"Peru"},{"id":"PN","value":"Pitcairn"},{"id":"PF","value":"Polinesia Franzosa"},{"id":"PL","value":"Pologna"},{"id":"PT","value":"Portugal"},{"id":"PR","value":"Puerto Rico"},{"id":"GB","value":"Reginavel Un\u00ec"},{"id":"HK","value":"Regiun d\u2019administraziun speziala da Hongkong, China"},{"id":"MO","value":"Regiun d\u2019administraziun speziala Macao, China"},{"id":"CF","value":"Republica Centralafricana"},{"id":"CD","value":"Republica Democratica dal Congo"},{"id":"DO","value":"Republica Dominicana"},{"id":"CZ","value":"Republica Tscheca"},{"id":"RE","value":"R\u00e9union"},{"id":"RW","value":"Ruanda"},{"id":"RO","value":"Rumenia"},{"id":"RU","value":"Russia"},{"id":"EH","value":"Sahara Occidentala"},{"id":"KN","value":"Saint Kitts e Nevis"},{"id":"LC","value":"Saint Lucia"},{"id":"MF","value":"Saint Martin"},{"id":"PM","value":"Saint Pierre e Miquelon"},{"id":"VC","value":"Saint Vincent e las Grenadinas"},{"id":"SB","value":"Salomonas"},{"id":"ZM","value":"Sambia"},{"id":"WS","value":"Samoa"},{"id":"AS","value":"Samoa Americana"},{"id":"SM","value":"San Marino"},{"id":"ST","value":"S\u00e3o Tom\u00e9 e Principe"},{"id":"SN","value":"Senegal"},{"id":"RS","value":"Serbia"},{"id":"SC","value":"Seychellas"},{"id":"SL","value":"Sierra Leone"},{"id":"ZW","value":"Simbabwe"},{"id":"SG","value":"Singapur"},{"id":"SX","value":"Sint Maarten"},{"id":"SY","value":"Siria"},{"id":"SK","value":"Slovachia"},{"id":"SI","value":"Slovenia"},{"id":"SO","value":"Somalia"},{"id":"BL","value":"Son Barth\u00e9lemy"},{"id":"SH","value":"Sontg\u2019Elena"},{"id":"SS","value":"South Sudan"},{"id":"ES","value":"Spagna"},{"id":"LK","value":"Sri Lanka"},{"id":"US","value":"Stadis Unids da l\u2019America"},{"id":"SD","value":"Sudan"},{"id":"SR","value":"Surinam"},{"id":"SJ","value":"Svalbard e Jan Mayen"},{"id":"SE","value":"Svezia"},{"id":"CH","value":"Svizra"},{"id":"SZ","value":"Swaziland"},{"id":"TJ","value":"Tadschikistan"},{"id":"TH","value":"Tailanda"},{"id":"TW","value":"Taiwan"},{"id":"TZ","value":"Tansania"},{"id":"IO","value":"Territori Britannic en l\u2019Ocean Indic"},{"id":"PS","value":"Territori Palestinais"},{"id":"TF","value":"Territoris Franzos Meridiunals"},{"id":"TL","value":"Timor da l\u2019Ost"},{"id":"TR","value":"Tirchia"},{"id":"TG","value":"Togo"},{"id":"TK","value":"Tokelau"},{"id":"TO","value":"Tonga"},{"id":"TT","value":"Trinidad e Tobago"},{"id":"TA","value":"Tristan da Cunha"},{"id":"TD","value":"Tschad"},{"id":"TN","value":"Tunesia"},{"id":"TM","value":"Turkmenistan"},{"id":"TV","value":"Tuvalu"},{"id":"UA","value":"Ucraina"},{"id":"UG","value":"Uganda"},{"id":"HU","value":"Ungaria"},{"id":"UY","value":"Uruguay"},{"id":"UZ","value":"Usbekistan"},{"id":"VU","value":"Vanuatu"},{"id":"VE","value":"Venezuela"},{"id":"VN","value":"Vietnam"},{"id":"WF","value":"Wallis e Futuna"}]
