<?xml version="1.0" encoding="utf-8"?>
<countries><country><iso>AF</iso><name>Afganistan</name></country><country><iso>ZA</iso><name>Afrika e Jugut</name></country><country><iso>DZ</iso><name>Algjeri</name></country><country><iso>AD</iso><name>Andorrë</name></country><country><iso>AO</iso><name>Angolë</name></country><country><iso>AI</iso><name>Anguilë</name></country><country><iso>AQ</iso><name>Antarktikë</name></country><country><iso>AG</iso><name>Antigua e Barbuda</name></country><country><iso>SA</iso><name>Arabia Saudite</name></country><country><iso>AR</iso><name>Argjentinë</name></country><country><iso>AM</iso><name>Armeni</name></country><country><iso>AW</iso><name>Arubë</name></country><country><iso>AU</iso><name>Australi</name></country><country><iso>AT</iso><name>Austri</name></country><country><iso>AZ</iso><name>Azerbajxhan</name></country><country><iso>BS</iso><name>Bahamas</name></country><country><iso>BH</iso><name>Bahrein</name></country><country><iso>BD</iso><name>Bangladesh</name></country><country><iso>BB</iso><name>Barbados</name></country><country><iso>BE</iso><name>Belgjikë</name></country><country><iso>BZ</iso><name>Belizë</name></country><country><iso>BJ</iso><name>Benin</name></country><country><iso>BM</iso><name>Bermudë</name></country><country><iso>BY</iso><name>Bjellorusi</name></country><country><iso>BO</iso><name>Bolivi</name></country><country><iso>BA</iso><name>Bosnjë-Hercegovinë</name></country><country><iso>BW</iso><name>Botsvanë</name></country><country><iso>BR</iso><name>Brazil</name></country><country><iso>CI</iso><name>Bregu i Fildishtë</name></country><country><iso>BN</iso><name>Brunej</name></country><country><iso>BG</iso><name>Bullgari</name></country><country><iso>BF</iso><name>Burkina Faso</name></country><country><iso>BI</iso><name>Burund</name></country><country><iso>BT</iso><name>Butan</name></country><country><iso>TD</iso><name>Çad</name></country><country><iso>DK</iso><name>Danimarkë</name></country><country><iso>DG</iso><name>Diego Garsia</name></country><country><iso>DM</iso><name>Dominikë</name></country><country><iso>EG</iso><name>Egjipt</name></country><country><iso>EC</iso><name>Ekuador</name></country><country><iso>SV</iso><name>El Salvador</name></country><country><iso>AE</iso><name>Emiratet e Bashkuara Arabe</name></country><country><iso>ER</iso><name>Eritre</name></country><country><iso>EE</iso><name>Estoni</name></country><country><iso>ET</iso><name>Etiopi</name></country><country><iso>PH</iso><name>Filipine</name></country><country><iso>FI</iso><name>Finlandë</name></country><country><iso>FJ</iso><name>Fixhi</name></country><country><iso>FR</iso><name>Francë</name></country><country><iso>GA</iso><name>Gabon</name></country><country><iso>GM</iso><name>Gambi</name></country><country><iso>GH</iso><name>Ganë</name></country><country><iso>GD</iso><name>Grenadë</name></country><country><iso>GL</iso><name>Grenlandë</name></country><country><iso>GR</iso><name>Greqi</name></country><country><iso>GP</iso><name>Guadalupe</name></country><country><iso>GF</iso><name>Guajana Franceze</name></country><country><iso>GY</iso><name>Guajanë</name></country><country><iso>GU</iso><name>Guam</name></country><country><iso>GT</iso><name>Guatemalë</name></country><country><iso>GG</iso><name>Guernsej</name></country><country><iso>GN</iso><name>Guine</name></country><country><iso>GW</iso><name>Guine-Bisau</name></country><country><iso>GQ</iso><name>Guineja Ekuatoriale</name></country><country><iso>GE</iso><name>Gjeorgji</name></country><country><iso>DE</iso><name>Gjermani</name></country><country><iso>GI</iso><name>Gjibraltar</name></country><country><iso>HT</iso><name>Haiti</name></country><country><iso>NL</iso><name>Holandë</name></country><country><iso>HN</iso><name>Honduras</name></country><country><iso>HU</iso><name>Hungari</name></country><country><iso>IN</iso><name>Indi</name></country><country><iso>ID</iso><name>Indonezi</name></country><country><iso>IQ</iso><name>Irak</name></country><country><iso>IR</iso><name>Iran</name></country><country><iso>IE</iso><name>Irlandë</name></country><country><iso>IS</iso><name>Islandë</name></country><country><iso>AX</iso><name>Ishujt Alandë</name></country><country><iso>MP</iso><name>Ishujt e Marianës Veriore</name></country><country><iso>VI</iso><name>Ishujt e Virgjër Amerikanë</name></country><country><iso>VG</iso><name>Ishujt e Virgjër Britanikë</name></country><country><iso>FO</iso><name>Ishujt Faroe</name></country><country><iso>FK</iso><name>Ishujt Folklandë</name></country><country><iso>KY</iso><name>Ishujt Kajmanë</name></country><country><iso>IC</iso><name>Ishujt Kanarie</name></country><country><iso>CC</iso><name>Ishujt Kokos</name></country><country><iso>CK</iso><name>Ishujt Kukë</name></country><country><iso>MH</iso><name>Ishujt Marshallë</name></country><country><iso>NF</iso><name>Ishujt Norfolkë</name></country><country><iso>UM</iso><name>Ishujt periferikë të SHBA-së</name></country><country><iso>PN</iso><name>Ishujt Pitkernë</name></country><country><iso>SB</iso><name>Ishujt Solomonë</name></country><country><iso>TC</iso><name>Ishujt Turke dhe Kaike</name></country><country><iso>AC</iso><name>Ishulli Asenshion</name></country><country><iso>CX</iso><name>Ishulli i Krishtlindjes</name></country><country><iso>IM</iso><name>Ishulli i Manit</name></country><country><iso>IT</iso><name>Itali</name></country><country><iso>IL</iso><name>Izrael</name></country><country><iso>JP</iso><name>Japoni</name></country><country><iso>YE</iso><name>Jemen</name></country><country><iso>JO</iso><name>Jordani</name></country><country><iso>NC</iso><name>Kaledonia e Re</name></country><country><iso>KH</iso><name>Kamboxhia</name></country><country><iso>CM</iso><name>Kamerun</name></country><country><iso>CA</iso><name>Kanada</name></country><country><iso>BQ</iso><name>Karaibet holandeze</name></country><country><iso>QA</iso><name>Katar</name></country><country><iso>KZ</iso><name>Kazakistan</name></country><country><iso>KE</iso><name>Kenia</name></country><country><iso>CV</iso><name>Kepi i Gjelbër</name></country><country><iso>CL</iso><name>Kili</name></country><country><iso>CN</iso><name>Kinë</name></country><country><iso>KG</iso><name>Kirgistan</name></country><country><iso>CO</iso><name>Kolumbi</name></country><country><iso>KM</iso><name>Komore</name></country><country><iso>CG</iso><name>Kongo-Brazavilë</name></country><country><iso>CD</iso><name>Kongo-Kinshasa</name></country><country><iso>KR</iso><name>Koreja e Jugut</name></country><country><iso>KP</iso><name>Koreja e Veriut</name></country><country><iso>XK</iso><name>Kosovë</name></country><country><iso>CR</iso><name>Kosta Rikë</name></country><country><iso>HR</iso><name>Kroaci</name></country><country><iso>CU</iso><name>Kubë</name></country><country><iso>CW</iso><name>Kuraçao</name></country><country><iso>KW</iso><name>Kuvajt</name></country><country><iso>LA</iso><name>Laos</name></country><country><iso>LS</iso><name>Lesoto</name></country><country><iso>LV</iso><name>Letoni</name></country><country><iso>LB</iso><name>Liban</name></country><country><iso>LR</iso><name>Liberi</name></country><country><iso>LY</iso><name>Libi</name></country><country><iso>LI</iso><name>Lihtënshtajn</name></country><country><iso>LT</iso><name>Lituani</name></country><country><iso>LU</iso><name>Luksemburg</name></country><country><iso>MG</iso><name>Madagaskar</name></country><country><iso>YT</iso><name>Majotë</name></country><country><iso>MY</iso><name>Malajzi</name></country><country><iso>MW</iso><name>Malavi</name></country><country><iso>MV</iso><name>Maldive</name></country><country><iso>ML</iso><name>Mali</name></country><country><iso>ME</iso><name>Mali i Zi</name></country><country><iso>MT</iso><name>Maltë</name></country><country><iso>MK</iso><name>Maqedoni</name></country><country><iso>MA</iso><name>Marok</name></country><country><iso>MQ</iso><name>Martinik</name></country><country><iso>MR</iso><name>Mauritani</name></country><country><iso>MU</iso><name>Mauritius</name></country><country><iso>GB</iso><name>Mbretëria e Bashkuar</name></country><country><iso>MX</iso><name>Meksikë</name></country><country><iso>MM</iso><name>Mianmar (Burma)</name></country><country><iso>FM</iso><name>Mikronezi</name></country><country><iso>MD</iso><name>Moldavi</name></country><country><iso>MC</iso><name>Monako</name></country><country><iso>MN</iso><name>Mongoli</name></country><country><iso>MS</iso><name>Montserat</name></country><country><iso>MZ</iso><name>Mozambik</name></country><country><iso>NA</iso><name>Namibi</name></country><country><iso>NR</iso><name>Nauru</name></country><country><iso>NP</iso><name>Nepal</name></country><country><iso>NE</iso><name>Niger</name></country><country><iso>NG</iso><name>Nigeri</name></country><country><iso>NI</iso><name>Nikaragua</name></country><country><iso>NU</iso><name>Niue</name></country><country><iso>NO</iso><name>Norvegji</name></country><country><iso>OM</iso><name>Oman</name></country><country><iso>PK</iso><name>Pakistan</name></country><country><iso>PW</iso><name>Palau</name></country><country><iso>PA</iso><name>Panama</name></country><country><iso>PG</iso><name>Papua Guineja e Re</name></country><country><iso>PY</iso><name>Paraguai</name></country><country><iso>PE</iso><name>Peru</name></country><country><iso>PF</iso><name>Polinezia Franceze</name></country><country><iso>PL</iso><name>Poloni</name></country><country><iso>PR</iso><name>Porto Riko</name></country><country><iso>PT</iso><name>Portugali</name></country><country><iso>CY</iso><name>Qipro</name></country><country><iso>KI</iso><name>Qiribati</name></country><country><iso>CF</iso><name>Republika Afrikano-Qendrore</name></country><country><iso>CZ</iso><name>Republika Çeke</name></country><country><iso>DO</iso><name>Republika Dominikane</name></country><country><iso>RE</iso><name>Reunion</name></country><country><iso>RW</iso><name>Ruandë</name></country><country><iso>RO</iso><name>Rumani</name></country><country><iso>RU</iso><name>Rusi</name></country><country><iso>HK</iso><name>RVAK i Hong Kongut</name></country><country><iso>MO</iso><name>RVAK i Makaos</name></country><country><iso>EH</iso><name>Saharaja Perëndimore</name></country><country><iso>WS</iso><name>Samoa</name></country><country><iso>AS</iso><name>Samoa Amerikane</name></country><country><iso>SM</iso><name>San Marino</name></country><country><iso>ST</iso><name>Sao Tome e Prinsipe</name></country><country><iso>SN</iso><name>Senegali</name></country><country><iso>RS</iso><name>Serbi</name></country><country><iso>SL</iso><name>Siera Leone</name></country><country><iso>SG</iso><name>Singapor</name></country><country><iso>SY</iso><name>Siri</name></country><country><iso>SC</iso><name>Sishel</name></country><country><iso>SK</iso><name>Sllovaki</name></country><country><iso>SI</iso><name>Slloveni</name></country><country><iso>SO</iso><name>Somali</name></country><country><iso>ES</iso><name>Spanjë</name></country><country><iso>LK</iso><name>Sri Lankë</name></country><country><iso>SD</iso><name>Sudan</name></country><country><iso>SS</iso><name>Sudani i Jugut</name></country><country><iso>SE</iso><name>Suedi</name></country><country><iso>SR</iso><name>Surinami</name></country><country><iso>SJ</iso><name>Svalbard e Zhan Majen</name></country><country><iso>SZ</iso><name>Svazilandë</name></country><country><iso>BL</iso><name>Shën Bartolemeo</name></country><country><iso>SH</iso><name>Shën Helena</name></country><country><iso>KN</iso><name>Shën Kits e Nevis</name></country><country><iso>LC</iso><name>Shën Luçia</name></country><country><iso>MF</iso><name>Shën Martin</name></country><country><iso>SX</iso><name>Shën Martin (Sint Maarten-pjesa e Mbretërisë së Holandës)</name></country><country><iso>PM</iso><name>Shën Peir dhe Mikuelon</name></country><country><iso>VC</iso><name>Shën Vinsent dhe Grenadinet</name></country><country><iso>AL</iso><name>Shqipëri</name></country><country><iso>US</iso><name>Shtetet e Bashkuara të Amerikës</name></country><country><iso>TH</iso><name>Tajlandë</name></country><country><iso>TW</iso><name>Tajvan</name></country><country><iso>TZ</iso><name>Tanzani</name></country><country><iso>TJ</iso><name>Taxhikistan</name></country><country><iso>TF</iso><name>Territoret Australiane Franceze</name></country><country><iso>PS</iso><name>Territoret Palestineze</name></country><country><iso>IO</iso><name>Territori Britanik i Oqeanit Indian</name></country><country><iso>TL</iso><name>Timori Lindor</name></country><country><iso>TG</iso><name>Togo</name></country><country><iso>TK</iso><name>Tokelau</name></country><country><iso>TO</iso><name>Tonga</name></country><country><iso>TT</iso><name>Trinidad e Tobago</name></country><country><iso>TA</iso><name>Tristan da Kuna</name></country><country><iso>TN</iso><name>Tunizi</name></country><country><iso>TM</iso><name>Turkmenistan</name></country><country><iso>TR</iso><name>Turqi</name></country><country><iso>TV</iso><name>Tuvalu</name></country><country><iso>EA</iso><name>Theuta e Melila</name></country><country><iso>UG</iso><name>Ugandë</name></country><country><iso>UA</iso><name>Ukrainë</name></country><country><iso>WF</iso><name>Uollis e Futina</name></country><country><iso>UY</iso><name>Uruguai</name></country><country><iso>UZ</iso><name>Uzbekistan</name></country><country><iso>VU</iso><name>Vanuatu</name></country><country><iso>VA</iso><name>Vatikan</name></country><country><iso>VE</iso><name>Venezuelë</name></country><country><iso>VN</iso><name>Vietnam</name></country><country><iso>JM</iso><name>Xhamajkë</name></country><country><iso>JE</iso><name>Xhersej</name></country><country><iso>DJ</iso><name>Xhibut</name></country><country><iso>GS</iso><name>Xhorxha Jugore dhe Ishujt Senduiç të Jugut</name></country><country><iso>ZM</iso><name>Zambi</name></country><country><iso>NZ</iso><name>Zelanda e Re</name></country><country><iso>ZW</iso><name>Zimbabve</name></country><country><iso>CH</iso><name>Zvicër</name></country></countries>
