<?xml version="1.0" encoding="utf-8"?>
<resources xmlns:tools="http://schemas.android.com/tools">
  <string name="country_ER">ꔀꔸꔳꕟ</string>
  <string name="country_BZ">ꔆꔷꔘ</string>
  <string name="country_SL">ꔋꕩ ꕒꕌꖺ ꕸꖃꔀ</string>
  <string name="country_TL">ꔎꔒ ꗃ ꔳꗞꖻ</string>
  <string name="country_LY">ꔒꔫꕩ</string>
  <string name="country_LB">ꔒꕑꗟꘋ</string>
  <string name="country_RE">ꔓꗠꖻ</string>
  <string name="country_SC">ꔖꗼꔷ</string>
  <string name="country_CL">ꔚꔷ</string>
  <string name="country_IO">ꔛꔟꔻ ꔤꔺꕩ ꗛꔤꘂ ꕗꕴꔀ ꕮ</string>
  <string name="country_VG">ꔛꔟꔻ ꗩꗡ ꗏ ꖷꖬ ꔳꘋꗣ</string>
  <string name="country_JP">ꔛꗨꗢ</string>
  <string name="country_YE">ꔝꘈꘋ</string>
  <string name="country_KY">ꔞꔀꕮꘋ ꔳꘋꗣ</string>
  <string name="country_CV">ꔞꔪ ꗲꔵ ꔳꘋꗣ</string>
  <string name="country_KE">ꔞꕰ</string>
  <string name="country_ET">ꔤꔳꖎꔪꕩ</string>
  <string name="country_IN">ꔤꔺꕩ</string>
  <string name="country_IT">ꔤꕚꔷ</string>
  <string name="country_IQ">ꔤꕟꕃ</string>
  <string name="country_IR">ꔤꕟꘋ</string>
  <string name="country_ID">ꔤꖆꕇꔻꕩ</string>
  <string name="country_PN">ꔪꔳꕪꕆ</string>
  <string name="country_PR">ꔪꖳꕿ ꔸꖏ</string>
  <string name="country_PH">ꔱꔒꔪꘋ</string>
  <string name="country_FJ">ꔱꔤꕀ</string>
  <string name="country_FI">ꔱꘋ ꖨꕮꕊ</string>
  <string name="country_LS">ꔷꖇꕿ</string>
  <string name="country_LT">ꔷꖤꔃꕇꕰ</string>
  <string name="country_LI">ꔷꗿꘋꔻꗳꘋ</string>
  <string name="country_SN">ꔻꕇꕭꕌ</string>
  <string name="country_SY">ꔻꕩꘋ</string>
  <string name="country_SG">ꔻꕬꕶꕱ</string>
  <string name="country_SI">ꔻꖃꔍꕇꕰ</string>
  <string name="country_SK">ꔻꖃꕙꕃꕩ</string>
  <string name="country_PM">ꔻꘋ ꔪꘂ ꗪ ꕆꔞꗏꘋ</string>
  <string name="country_VC">ꔻꘋ ꔲꘋꔻꘋ ꗪ ꖶꔓꕯꔵꘋ ꖸ</string>
  <string name="country_KN">ꔻꘋ ꕃꔳꔻ ꗪ ꔕꔲꔻ</string>
  <string name="country_LC">ꔻꘋ ꖨꔻꕩ</string>
  <string name="country_SH">ꔻꘋ ꗥꔷꕯ</string>
  <string name="country_NZ">ꔽꔤ ꖨꕮ ꕯꕮꕊ</string>
  <string name="country_ZW">ꔽꕓꖜꔃ</string>
  <string name="country_DJ">ꕀꖜꔳ</string>
  <string name="country_GI">ꕀꖜꕟꕚ</string>
  <string name="country_KI">ꕃꔸꕑꔳ</string>
  <string name="country_KG">ꕃꕅꔻꕚꘋ</string>
  <string name="country_CU">ꕃꖳꕑ</string>
  <string name="country_GN">ꕅꔤꕇ</string>
  <string name="country_GW">ꕅꔤꕇ ꔫꕢꕴ</string>
  <string name="country_EG">ꕆꔖꕞ</string>
  <string name="country_MM">ꕆꕩꘋꕮ</string>
  <string name="country_FM">ꕆꖏꕇꔻꕩ</string>
  <string name="country_NP">ꕇꕐꔷ</string>
  <string name="country_NI">ꕇꕪꕟꖶꕎ</string>
  <string name="country_IE">ꕉꔓ ꖨꕮꕊ</string>
  <string name="country_IS">ꕉꔤꔻ ꖨꕮꕊ</string>
  <string name="country_ZA">ꕉꔱꔸꕪ ꗛꔤ ꔒꘋꗣ ꗏ ꕸꖃꔀ</string>
  <string name="country_CF">ꕉꔱꔸꕪ ꗳ ꗳ ꕸꖃꔀ</string>
  <string name="country_AF">ꕉꔱꕭꔕꔻꕚꘋ</string>
  <string name="country_DZ">ꕉꔷꔠꔸꕩ</string>
  <string name="country_AL">ꕉꔷꕑꕇꕩ</string>
  <string name="country_AI">ꕉꕄꕞ</string>
  <string name="country_AM">ꕉꕆꕯ</string>
  <string name="country_AZ">ꕉꕤꕑꔤꕧꘋ</string>
  <string name="country_AD">ꕉꖆꕟ</string>
  <string name="country_AO">ꕉꖐꕞ</string>
  <string name="country_AW">ꕉꖩꕑ</string>
  <string name="country_AR">ꕉꘀꘋꔳꕯ</string>
  <string name="country_AG">ꕉꘋꔳꖶꕎ ꗪ ꕑꖜꕜ</string>
  <string name="country_HT">ꕌꔤꔳ</string>
  <string name="country_WF">ꕎꔷꔻ ꗪ ꖢꖤꕯ</string>
  <string name="country_PS">ꕐꔒꔻꔳꕯ ꔎꔒ ꕀꔤ ꗛꔤ ꕞ ꗱ ꗪ ꕭꕌꕤ</string>
  <string name="country_PK">ꕐꕃꔻꕚꘋ</string>
  <string name="country_PY">ꕐꕟꗝꔀ</string>
  <string name="country_PA">ꕐꕯꕮ</string>
  <string name="country_PW">ꕐꖃ</string>
  <string name="country_PG">ꕐꖛꕎ ꕅꔤꕇ ꕯꕮꕊ</string>
  <string name="country_ES">ꕐꘊꔧ</string>
  <string name="country_BB">ꕑꔆꖁꔻ</string>
  <string name="country_BD">ꕑꕅꕞꗵꔼ</string>
  <string name="country_IL">ꕑꕇꔻꕞꔤꕞ</string>
  <string name="country_BS">ꕑꕌꕮꔻ</string>
  <string name="country_BH">ꕑꗸꘋ</string>
  <string name="country_FK">ꕘꔷꕃ ꖨꕮ ꔳꘋꗣ</string>
  <string name="country_VE">ꕙꔳꕪꘋ ꕸꖃꔀ</string>
  <string name="country_VU">ꕙꖸꕎꖤ</string>
  <string name="country_TH">ꕚꔤ ꖨꕮꕊ</string>
  <string name="country_TW">ꕚꔤꕎꘋ</string>
  <string name="country_TJ">ꕚꕀꕃꔻꕚꘋ</string>
  <string name="country_TV">ꕚꖣꖨ</string>
  <string name="country_TZ">ꕚꘋꕤꕇꕰ</string>
  <string name="country_DK">ꕜꕇꕮꕃ</string>
  <string name="country_LR">ꕞꔤꔫꕩ</string>
  <string name="country_LV">ꕞꔳꔲꕩ</string>
  <string name="country_SA">ꕞꕌꖝ ꕸꖃꔀ</string>
  <string name="country_LA">ꕞꕴꔻ</string>
  <string name="country_RW">ꕟꖙꕡ</string>
  <string name="country_ST">ꕢꕴ ꕿꔈ ꗪ ꕉ ꕮꔧ ꕗꕴꔀ</string>
  <string name="country_WS">ꕢꕹꖙꕉ</string>
  <string name="country_CY">ꕢꗡꖛꗐꔻ</string>
  <string name="country_ZM">ꕤꔭꕩ</string>
  <string name="country_CN">ꕦꔤꕯ</string>
  <string name="country_TD">ꕦꔵ</string>
  <string name="country_GL">ꕧꕓ ꖴꕎ ꖨꕮꕊ</string>
  <string name="country_DE">ꕧꕮꔧ</string>
  <string name="country_JM">ꕧꕮꔧꕪ</string>
  <string name="country_CM">ꕪꔈꖩꘋ</string>
  <string name="country_NC">ꕪꔷꖁꕇꕰ ꕯꕮꕊ</string>
  <string name="country_QA">ꕪꕚꕌ</string>
  <string name="country_KZ">ꕪꕤꔻꕚꘋ</string>
  <string name="country_CA">ꕪꕯꕜ</string>
  <string name="country_KH">ꕪꕹꔵꕩ</string>
  <string name="country_GM">ꕭꔭꕩ</string>
  <string name="country_GH">ꕭꕌꕯ</string>
  <string name="country_GA">ꕭꕷꘋ</string>
  <string name="country_MY">ꕮꔒꔻꕩ</string>
  <string name="country_MK">ꕮꔖꖁꕇꕰ</string>
  <string name="country_MQ">ꕮꔳꕇꕃ</string>
  <string name="country_ML">ꕮꔷ</string>
  <string name="country_MV">ꕮꔷꕜꔍ</string>
  <string name="country_SM">ꕮꔸꖆ ꕢꘋ</string>
  <string name="country_MT">ꕮꕊꕚ</string>
  <string name="country_MH">ꕮꕊꕣ ꔳꘋꗣ</string>
  <string name="country_MG">ꕮꕜꕭꔻꕪ</string>
  <string name="country_MW">ꕮꕞꕌꔨ</string>
  <string name="country_YT">ꕮꗚꔎ</string>
  <string name="country_NG">ꕯꔤꕀꔸꕩ</string>
  <string name="country_NE">ꕯꔤꕧ</string>
  <string name="country_NA">ꕯꕆꔫꕩ</string>
  <string name="country_OM">ꕱꕮꘋ</string>
  <string name="country_US">ꕶꕱ</string>
  <string name="country_AS">ꕶꕱ ꕢꕹꕎ</string>
  <string name="country_VI">ꕶꕱ ꗩꗡ ꗏ ꖷꖬ ꔳꘋꗣ</string>
  <string name="country_PT">ꕶꕿꕃꔤ ꕸꖃꔀ</string>
  <string name="country_PL">ꕶꗷꘋ</string>
  <string name="country_BO">ꕷꔷꔲꕩ</string>
  <string name="country_BA">ꕷꔻꕇꕰ ꗪ ꗥꕤꖑꔲꕯ</string>
  <string name="country_BF">ꕷꕃꕯ ꕘꖇ</string>
  <string name="country_BW">ꕷꖬꕎꕯ</string>
  <string name="country_MZ">ꕹꕤꔭꕃ</string>
  <string name="country_TK">ꕿꔞꖃ</string>
  <string name="country_TG">ꕿꖑ</string>
  <string name="country_DM">ꖁꕆꕇꕪ</string>
  <string name="country_DO">ꖁꕆꕇꕪꘋ ꕸꕱꔀ</string>
  <string name="country_RO">ꖄꕆꕇꕰ</string>
  <string name="country_NR">ꖆꖩ</string>
  <string name="country_SO">ꖇꕮꔷꕩ</string>
  <string name="country_HR">ꖏꔓꔻꕩ</string>
  <string name="country_CI">ꖏꔳ ꕾꕎ</string>
  <string name="country_KR">ꖏꔸꕩ ꗛꔤ ꔒꘋꗣ ꗏ</string>
  <string name="country_KP">ꖏꔸꕩ ꗛꔤ ꕪꘋꗒ</string>
  <string name="country_CR">ꖏꔻꕚ ꔸꕪ</string>
  <string name="country_CK">ꖏꕃ ꔳꘋꗣ</string>
  <string name="country_KM">ꖏꕹꖄꔻ</string>
  <string name="country_CG">ꖏꖐ</string>
  <string name="country_CD">ꖏꖐ ꗵꗞꖴꕟꔎ ꕸꖃꔀ</string>
  <string name="country_MD">ꖒꔷꖁꕙ</string>
  <string name="country_GB">ꖕꕯꔤꗳ</string>
  <string name="country_BT">ꖜꕚꘋ</string>
  <string name="country_BR">ꖜꕟꔘꔀ</string>
  <string name="country_BI">ꖜꖩꔺ</string>
  <string name="country_BN">ꖜꖩꘉꔧ</string>
  <string name="country_FR">ꖢꕟꘋꔻ</string>
  <string name="country_TT">ꖤꔸꔕꕜ ꗪ ꕿꔆꖑ</string>
  <string name="country_TN">ꖤꕇꔻꕩ</string>
  <string name="country_GQ">ꖦꕰꕊ ꗳ ꕅꔤꕇ</string>
  <string name="country_CH">ꖬꔃꕤ ꖨꕮꕊ</string>
  <string name="country_SE">ꖬꔨꗵꘋ</string>
  <string name="country_LK">ꖬꔸ ꕞꘋꕪ</string>
  <string name="country_SR">ꖬꔸꕯꔈ</string>
  <string name="country_SZ">ꖬꕎꔽ ꖨꕮꕊ</string>
  <string name="country_SB">ꖬꕞꔤꕮꕊꕯ ꔳꘋꗣ</string>
  <string name="country_SD">ꖬꗵꘋ</string>
  <string name="country_UY">ꖳꔓꗝꔀ</string>
  <string name="country_UG">ꖳꕭꕡ</string>
  <string name="country_AE">ꖳꕯꔤꗳ ꕉꕟꔬ ꗡꕆꔓꔻ</string>
  <string name="country_UA">ꖳꖴꔓꘋ</string>
  <string name="country_UZ">ꖳꗩꕃꔻꕚꘋ</string>
  <string name="country_KW">ꖴꔃꔳ</string>
  <string name="country_GT">ꖶꕎꔎꕮꕞ</string>
  <string name="country_GP">ꖶꕎꔐꖨꔅ</string>
  <string name="country_GU">ꖶꕎꕆ</string>
  <string name="country_GD">ꖶꕟꕯꕜ</string>
  <string name="country_GY">ꖶꕩꕯ</string>
  <string name="country_NU">ꖸꔃꔤ</string>
  <string name="country_AT">ꖺꔻꖤꕎ</string>
  <string name="country_AU">ꖺꖬꖤꔃꔷꕩ</string>
  <string name="country_HN">ꖽꖫꕟ</string>
  <string name="country_HU">ꖽꘋꕭꔓ</string>
  <string name="country_BG">ꗂꔠꔸꕩ</string>
  <string name="country_TO">ꗋꕬ</string>
  <string name="country_TR">ꗋꖺꕃ</string>
  <string name="country_TC">ꗋꖺꕃꔻ ꗪ ꕪꔤꖏꔻ ꔳꘋꗣ</string>
  <string name="country_TM">ꗋꖺꕃꕮꕇꔻꕚꘋ</string>
  <string name="country_LU">ꗏꔻꘋꗂꖺ</string>
  <string name="country_RU">ꗐꖺꔻꕩ</string>
  <string name="country_GE">ꗘꖺꕀꕩ</string>
  <string name="country_JO">ꗘꖺꗵꘋ</string>
  <string name="country_MP">ꗛꔤ ꕪꘋꗒ ꕮꔸꕩꕯ ꔳꘋꗣ</string>
  <string name="country_CO">ꗛꗏꔭꕩ</string>
  <string name="country_MR">ꗞꔓꔎꕇꕰ</string>
  <string name="country_MU">ꗞꔓꗔ</string>
  <string name="country_MA">ꗞꕟꖏ</string>
  <string name="country_MC">ꗞꕯꖏ</string>
  <string name="country_MN">ꗞꖐꔷꕩ</string>
  <string name="country_MS">ꗞꘋꔖꕟꔳ</string>
  <string name="country_NO">ꗟꖺꔃ</string>
  <string name="country_NF">ꗟꖺꗉ ꔳꘋꗣ</string>
  <string name="country_EE">ꗡꔻꕿꕇꕰ</string>
  <string name="country_EC">ꗡꖴꔃꗍ</string>
  <string name="country_SV">ꗡꗷ ꕢꔍꗍꖺ</string>
  <string name="country_GR">ꗥꗷꘋ</string>
  <string name="country_PE">ꗨꗡꖩ</string>
  <string name="country_BE">ꗩꕀꗚꘋ</string>
  <string name="country_BJ">ꗩꕇꘋ</string>
  <string name="country_BY">ꗩꕞꖩꔻ</string>
  <string name="country_BM">ꗩꖷꕜ</string>
  <string name="country_PF">ꗱꘋꔻ ꕶꔷꕇꔻꕩ</string>
  <string name="country_GF">ꗱꘋꔻ ꖶꕎꕯ</string>
  <string name="country_VN">ꗲꕇꖮꔃꕞ</string>
  <string name="country_CS">ꗻꗡꔫꕩ ꗪ ꗞꘋꔳꕇꖶꖄ</string>
  <string name="country_CZ">ꗿꕃ ꕸꖃꔀ</string>
  <string name="country_MX">ꘈꔻꖏ</string>
  <string name="country_NL">ꘉꕜ ꖨꕮꕊ</string>
  <string name="country_AN">ꘉꕜ ꖨꕮꕊ ꕉꘋꔳꔷ</string>
</resources>
