{"AF":"Afganistan","AX":"\u00c1land","AL":"Albania","DZ":"Algeria","AS":"Amerikanska S\u00e1moa","AD":"Andorra","AO":"Angola","AI":"Anguilla","AQ":"Antarktis","AG":"Antigua og Barbuda","AR":"Argentina","AM":"Armenia","AW":"Aruba","AC":"Ascensionoyggjin","AZ":"Aserbajdsjan","AU":"Avstralia","BS":"Bahamas","BH":"Bahrain","BD":"Bangladesj","BB":"Barbados","BE":"Belgia","BZ":"Belis","BJ":"Benin","BM":"Bermuda","BO":"Bolivia","BA":"Bosnia-Hersegovina","BW":"Botsvana","BR":"Brasilia","IO":"Bretsku Indiahavsoyggjarnar","BN":"Brunei","BG":"Bulgaria","BF":"Burkina Faso","MM":"Burma","BI":"Burundi","BT":"Butan","KY":"Caymanoyggjarnar","EA":"Ceuta og Melilla","CK":"Cooksoyggjarnar","CW":"Cura\u00e7ao","DK":"Danm\u00f8rk","DG":"Diego Garcia","DJ":"Djibouti","DO":"Domingo l\u00fd\u00f0veldi\u00f0","DM":"Dominika","EG":"Egyptaland","EC":"Ekvador","GQ":"Ekvator Guinea","SV":"El Salvador","ER":"Eritrea","EE":"Estland","ET":"Etiopia","TL":"Eystur-Timor","AT":"Eysturr\u00edki","FK":"Falklandsoyggjarnar","FJ":"Fiji","CI":"F\u00edlabeinsstrondin","PH":"Filipsoyggjar","FI":"Finnland","FR":"Frakland","GF":"Fransk Gujana","MF":"Fransk Saint Martin","PF":"Franska Polynesia","TF":"French Southern Territories","FO":"F\u00f8royar","GA":"Gabon","GM":"Gambia","GE":"Georgia","GH":"Ghana","GI":"Gibraltar","GD":"Grenada","GR":"Grikkaland","CV":"Gr\u00f8nh\u00f8vdaoyggjarnar","GL":"Gr\u00f8nland","GP":"Guadeloupe","GU":"Guam","GT":"Guatemala","GG":"Guernsey","GN":"Guinea","GW":"Guinea Bissau","GY":"Gujana","HT":"Haiti","HN":"Honduras","HK":"Hongkong","BY":"Hv\u00edtarussland","IN":"India","ID":"Indonesia","IQ":"Irak","IR":"Iran","IE":"\u00cdrland","IS":"\u00cdsland","IL":"\u00cdsrael","IT":"Italia","JM":"Jameika","JP":"Japan","YE":"Jemen","JE":"Jersey","CX":"J\u00f3laoyggjin","JO":"Jordania","KH":"Kambodja","CM":"Kamerun","CA":"Kanada","IC":"Kanar\u00edoyggjarnar","KZ":"Kasakstan","QA":"Katar","CZ":"Kekkia","KE":"Kenja","CL":"Kili","CN":"Kina","KG":"Kirgisia","KI":"Kiribati","TD":"Kjad","CC":"Kokosoyggjarnar","CO":"Kolombia","KM":"Komorooyggjarnar","CG":"Kongo","CD":"Kongo-Kinshasa","XK":"Kosovo","CR":"Kosta Rika","HR":"Kroatia","CU":"Kuba","KW":"Kuvait","CY":"K\u00fdpros","LA":"Laos","LS":"Lesoto","LV":"Lettland","LB":"Libanon","LR":"Liberia","LY":"Libya","LI":"Liktenstein","LT":"Litava","LU":"Luksemborg","MG":"Madagaskar","MO":"Makao","MK":"Maked\u00f3nia","MW":"Malavi","MV":"Maldivuoyggjarnar","MY":"Maleisia","ML":"Mali","MT":"Malta","IM":"Mann","MA":"Marokko","MH":"Marshalloyggjarnar","MQ":"Martinique","YT":"Mayotte","MX":"Meksiko","CF":"Mi\u00f0afrikal\u00fd\u00f0veldi\u00f0","FM":"Mikronesia","MD":"Moldova","MC":"Monako","MN":"Mongolia","ME":"Montenegro","MS":"Montserrat","MR":"M\u00f3ritania","MU":"M\u00f3ritius","MZ":"Mosambik","NA":"Namibia","NR":"Nauru","NP":"Nepal","NL":"Ni\u00f0urlond","BQ":"Ni\u00f0urlonds Karibia","SX":"Ni\u00f0urlonds Saint Martin","NE":"Niger","NG":"Nigeria","NI":"Nikaragua","NU":"Niue","KP":"Nor\u00f0ur-Korea","MP":"Nor\u00f0urmarianoyggjarnar","SD":"Nor\u00f0ursudan","NO":"Noreg","NF":"Norfolkoyggjin","NZ":"N\u00fd S\u00e6land","NC":"N\u00fd-Kaledonia","OM":"Oman","PK":"Pakistan","PW":"Palau","PS":"Palestinskt territorium","PA":"Panama","PG":"Papua N\u00fdguinea","PY":"Paraguei","PE":"Per\u00fa","PN":"Pitcairn","PL":"P\u00f3lland","PT":"Portugal","PR":"Puerto Rico","RE":"R\u00e9union","RW":"Ruanda","RO":"Rumenia","RU":"Russland","BL":"Saint Barth\u00e9lemy","SH":"Saint Helena","KN":"Saint Kitts og Nevis","LC":"Saint Lusia","PM":"Saint Pierre og Miquelon","VC":"Saint Vinsent og Grenadinoyggjar","SB":"S\u00e1lomonoyggjarnar","US":"Sambandsr\u00edki Amerika","VI":"Sambandsr\u00edki Amerikas J\u00f3mfr\u00faoyggjarnar","ZM":"Sambia","AE":"Sameindu Emirr\u00edkini","WS":"S\u00e1moa","SM":"San Marino","ST":"Sao Tome og Prinsipi","SA":"Saudi-Ar\u00e1bia","SN":"Senegal","RS":"Serbia","SC":"Seyskelloyggjarnar","SL":"Sierra Leone","ZW":"Simbabvi","SG":"Singapor","SK":"Slovakia","SI":"Slovenia","SO":"Somalia","ES":"Spania","LK":"Sri Lanka","GB":"St\u00f3ra Bretland","VG":"St\u00f3ra Bretlands J\u00f3mfr\u00faoyggjarnar","KR":"Su\u00f0ur-Korea","ZA":"Su\u00f0urafrikal\u00fd\u00f0veldi\u00f0","GS":"Su\u00f0urgeorgia","SS":"Su\u00f0ursudan","SR":"Surinam","SJ":"Svalbard og Jan Mayen","SZ":"Svasiland","CH":"Sveis","SE":"Sv\u00f8r\u00edki","SY":"Syria","TJ":"Tadsjikistan","TZ":"Tansania","TH":"Teiland","TW":"Teivan","TG":"Togo","TK":"Tokelau","TO":"Tonga","TT":"Trinidad og Tobago","TA":"Tristan da Cunha","TN":"Tunesia","TR":"Turkaland","TM":"Turkmenistan","TC":"Turks- og Caicosoyggjarnar","TV":"Tuvalu","DE":"T\u00fdskland","UM":"U.S. Outlying Islands","UG":"Uganda","UA":"Ukreina","HU":"Ungarn","UY":"Uruguei","UZ":"Usbekistan","VU":"Vanuatu","VA":"Vatikan","VE":"Venesuela","EH":"Vestursahara","VN":"Vietnam","WF":"Wallis og Futuna"}