<?xml version="1.0" encoding="utf-8"?>
<values><item><id>AF</id><![CDATA[Afghanistan]]><value/></item><item><id>ZA</id><![CDATA[Afrika Atsimo]]><value/></item><item><id>AX</id><![CDATA[Åland Islands]]><value/></item><item><id>AL</id><![CDATA[Albania]]><value/></item><item><id>DE</id><![CDATA[Alemaina]]><value/></item><item><id>DZ</id><![CDATA[Alzeria]]><value/></item><item><id>AD</id><![CDATA[Andorra]]><value/></item><item><id>GB</id><![CDATA[Angletera]]><value/></item><item><id>AO</id><![CDATA[Angola]]><value/></item><item><id>AI</id><![CDATA[Anguilla]]><value/></item><item><id>AQ</id><![CDATA[Antarctica]]><value/></item><item><id>AG</id><![CDATA[Antiga sy Barboda]]><value/></item><item><id>AU</id><![CDATA[Aostralia]]><value/></item><item><id>AT</id><![CDATA[Aotrisy]]><value/></item><item><id>SA</id><![CDATA[Arabia saodita]]><value/></item><item><id>AM</id><![CDATA[Armenia]]><value/></item><item><id>AW</id><![CDATA[Arobà]]><value/></item><item><id>AR</id><![CDATA[Arzantina]]><value/></item><item><id>AC</id><![CDATA[Ascension Island]]><value/></item><item><id>AZ</id><![CDATA[Azerbaidjan]]><value/></item><item><id>BS</id><![CDATA[Bahamas]]><value/></item><item><id>BH</id><![CDATA[Bahrain]]><value/></item><item><id>BD</id><![CDATA[Bangladesy]]><value/></item><item><id>BB</id><![CDATA[Barbady]]><value/></item><item><id>BY</id><![CDATA[Belarosy]]><value/></item><item><id>BZ</id><![CDATA[Belize]]><value/></item><item><id>BE</id><![CDATA[Belzika]]><value/></item><item><id>BJ</id><![CDATA[Benin]]><value/></item><item><id>BM</id><![CDATA[Bermioda]]><value/></item><item><id>BT</id><![CDATA[Bhotana]]><value/></item><item><id>BG</id><![CDATA[Biolgaria]]><value/></item><item><id>BO</id><![CDATA[Bolivia]]><value/></item><item><id>BF</id><![CDATA[Borkina Faso]]><value/></item><item><id>BI</id><![CDATA[Borondi]]><value/></item><item><id>BA</id><![CDATA[Bosnia sy Herzegovina]]><value/></item><item><id>BW</id><![CDATA[Botsoana]]><value/></item><item><id>BR</id><![CDATA[Brezila]]><value/></item><item><id>BN</id><![CDATA[Brunei]]><value/></item><item><id>IC</id><![CDATA[Canary Islands]]><value/></item><item><id>BQ</id><![CDATA[Caribbean Netherlands]]><value/></item><item><id>EA</id><![CDATA[Ceuta & Melilla]]><value/></item><item><id>CX</id><![CDATA[Christmas Island]]><value/></item><item><id>CC</id><![CDATA[Cocos (Keeling) Islands]]><value/></item><item><id>CI</id><![CDATA[Côte d’Ivoire]]><value/></item><item><id>CW</id><![CDATA[Curaçao]]><value/></item><item><id>DK</id><![CDATA[Danmarka]]><value/></item><item><id>DG</id><![CDATA[Diego Garcia]]><value/></item><item><id>DJ</id><![CDATA[Djiboti]]><value/></item><item><id>DM</id><![CDATA[Dominika]]><value/></item><item><id>EG</id><![CDATA[Ejypta]]><value/></item><item><id>EC</id><![CDATA[Ekoatera]]><value/></item><item><id>SV</id><![CDATA[El Salvador]]><value/></item><item><id>AE</id><![CDATA[Emirà Arabo mitambatra]]><value/></item><item><id>ER</id><![CDATA[Eritrea]]><value/></item><item><id>ES</id><![CDATA[Espaina]]><value/></item><item><id>EE</id><![CDATA[Estonia]]><value/></item><item><id>US</id><![CDATA[Etazonia]]><value/></item><item><id>ET</id><![CDATA[Ethiopia]]><value/></item><item><id>IO</id><![CDATA[Faridranomasina indiana britanika]]><value/></item><item><id>FO</id><![CDATA[Faroe Islands]]><value/></item><item><id>FJ</id><![CDATA[Fidji]]><value/></item><item><id>PH</id><![CDATA[Filipina]]><value/></item><item><id>FI</id><![CDATA[Finlandy]]><value/></item><item><id>VA</id><![CDATA[Firenen’i Vatikana]]><value/></item><item><id>FR</id><![CDATA[Frantsa]]><value/></item><item><id>TF</id><![CDATA[French Southern Territories]]><value/></item><item><id>GA</id><![CDATA[Gabon]]><value/></item><item><id>GM</id><![CDATA[Gambia]]><value/></item><item><id>GH</id><![CDATA[Ghana]]><value/></item><item><id>GW</id><![CDATA[Giné-Bisao]]><value/></item><item><id>GN</id><![CDATA[Ginea]]><value/></item><item><id>GP</id><![CDATA[Goadelopy]]><value/></item><item><id>GT</id><![CDATA[Goatemalà]]><value/></item><item><id>GD</id><![CDATA[Grenady]]><value/></item><item><id>GR</id><![CDATA[Gresy]]><value/></item><item><id>GL</id><![CDATA[Groenland]]><value/></item><item><id>GU</id><![CDATA[Guam]]><value/></item><item><id>GG</id><![CDATA[Guernsey]]><value/></item><item><id>GQ</id><![CDATA[Guinea Ekoatera]]><value/></item><item><id>GY</id><![CDATA[Guyana]]><value/></item><item><id>GF</id><![CDATA[Guyana frantsay]]><value/></item><item><id>HT</id><![CDATA[Haiti]]><value/></item><item><id>NL</id><![CDATA[Holanda]]><value/></item><item><id>HN</id><![CDATA[Hondiorasy]]><value/></item><item><id>HK</id><![CDATA[Hong Kong SAR China]]><value/></item><item><id>HU</id><![CDATA[Hongria]]><value/></item><item><id>ID</id><![CDATA[Indonezia]]><value/></item><item><id>IN</id><![CDATA[Indy]]><value/></item><item><id>IQ</id><![CDATA[Irak]]><value/></item><item><id>IR</id><![CDATA[Iran]]><value/></item><item><id>IE</id><![CDATA[Irlandy]]><value/></item><item><id>IS</id><![CDATA[Islandy]]><value/></item><item><id>IM</id><![CDATA[Isle of Man]]><value/></item><item><id>IL</id><![CDATA[Israely]]><value/></item><item><id>IT</id><![CDATA[Italia]]><value/></item><item><id>JM</id><![CDATA[Jamaïka]]><value/></item><item><id>JP</id><![CDATA[Japana]]><value/></item><item><id>JE</id><![CDATA[Jersey]]><value/></item><item><id>JO</id><![CDATA[Jordania]]><value/></item><item><id>KH</id><![CDATA[Kambôdja]]><value/></item><item><id>CM</id><![CDATA[Kamerona]]><value/></item><item><id>CA</id><![CDATA[Kanada]]><value/></item><item><id>QA</id><![CDATA[Katar]]><value/></item><item><id>KZ</id><![CDATA[Kazakhstan]]><value/></item><item><id>KE</id><![CDATA[Kenya]]><value/></item><item><id>CU</id><![CDATA[Kiobà]]><value/></item><item><id>KG</id><![CDATA[Kiordistan]]><value/></item><item><id>KI</id><![CDATA[Kiribati]]><value/></item><item><id>KW</id><![CDATA[Kôeity]]><value/></item><item><id>CO</id><![CDATA[Kôlômbia]]><value/></item><item><id>KM</id><![CDATA[Kômaoro]]><value/></item><item><id>CG</id><![CDATA[Kôngô]]><value/></item><item><id>KR</id><![CDATA[Korea Atsimo]]><value/></item><item><id>KP</id><![CDATA[Korea Avaratra]]><value/></item><item><id>XK</id><![CDATA[Kosovo]]><value/></item><item><id>CR</id><![CDATA[Kosta Rikà]]><value/></item><item><id>HR</id><![CDATA[Kroasia]]><value/></item><item><id>LA</id><![CDATA[Laôs]]><value/></item><item><id>RE</id><![CDATA[Larenion]]><value/></item><item><id>LS</id><![CDATA[Lesotho]]><value/></item><item><id>LV</id><![CDATA[Letonia]]><value/></item><item><id>LB</id><![CDATA[Libana]]><value/></item><item><id>LR</id><![CDATA[Liberia]]><value/></item><item><id>LY</id><![CDATA[Libya]]><value/></item><item><id>LU</id><![CDATA[Lioksamboro]]><value/></item><item><id>LI</id><![CDATA[Listenstein]]><value/></item><item><id>LT</id><![CDATA[Litoania]]><value/></item><item><id>MO</id><![CDATA[Macau SAR China]]><value/></item><item><id>MG</id><![CDATA[Madagasikara]]><value/></item><item><id>MK</id><![CDATA[Makedonia]]><value/></item><item><id>MY</id><![CDATA[Malaizia]]><value/></item><item><id>MW</id><![CDATA[Malaoì]]><value/></item><item><id>MV</id><![CDATA[Maldiva]]><value/></item><item><id>ML</id><![CDATA[Mali]]><value/></item><item><id>MT</id><![CDATA[Malta]]><value/></item><item><id>MU</id><![CDATA[Maorisy]]><value/></item><item><id>MR</id><![CDATA[Maoritania]]><value/></item><item><id>MA</id><![CDATA[Marôka]]><value/></item><item><id>MQ</id><![CDATA[Martinika]]><value/></item><item><id>YT</id><![CDATA[Mayôty]]><value/></item><item><id>MX</id><![CDATA[Meksika]]><value/></item><item><id>FM</id><![CDATA[Mikrônezia]]><value/></item><item><id>MD</id><![CDATA[Môldavia]]><value/></item><item><id>MC</id><![CDATA[Mônakô]]><value/></item><item><id>MN</id><![CDATA[Môngôlia]]><value/></item><item><id>ME</id><![CDATA[Montenegro]]><value/></item><item><id>MS</id><![CDATA[Montserrat]]><value/></item><item><id>MZ</id><![CDATA[Mozambika]]><value/></item><item><id>MM</id><![CDATA[Myanmar]]><value/></item><item><id>NA</id><![CDATA[Namibia]]><value/></item><item><id>NR</id><![CDATA[Naorò]]><value/></item><item><id>NP</id><![CDATA[Nepala]]><value/></item><item><id>NE</id><![CDATA[Niger]]><value/></item><item><id>NI</id><![CDATA[Nikaragoà]]><value/></item><item><id>NU</id><![CDATA[Nioé]]><value/></item><item><id>NG</id><![CDATA[Nizeria]]><value/></item><item><id>NO</id><![CDATA[Nôrvezy]]><value/></item><item><id>VG</id><![CDATA[Nosy britanika virijiny]]><value/></item><item><id>CV</id><![CDATA[Nosy Cap-Vert]]><value/></item><item><id>FK</id><![CDATA[Nosy Falkand]]><value/></item><item><id>KY</id><![CDATA[Nosy Kayman]]><value/></item><item><id>CK</id><![CDATA[Nosy Kook]]><value/></item><item><id>MP</id><![CDATA[Nosy Mariana Atsinanana]]><value/></item><item><id>MH</id><![CDATA[Nosy Marshall]]><value/></item><item><id>NF</id><![CDATA[Nosy Norfolk]]><value/></item><item><id>SB</id><![CDATA[Nosy Salomona]]><value/></item><item><id>TC</id><![CDATA[Nosy Turks sy Caïques]]><value/></item><item><id>VI</id><![CDATA[Nosy Virijiny Etazonia]]><value/></item><item><id>NC</id><![CDATA[Nouvelle-Calédonie]]><value/></item><item><id>NZ</id><![CDATA[Nouvelle-Zélande]]><value/></item><item><id>UG</id><![CDATA[Oganda]]><value/></item><item><id>UA</id><![CDATA[Okraina]]><value/></item><item><id>OM</id><![CDATA[Oman]]><value/></item><item><id>UY</id><![CDATA[Orogoay]]><value/></item><item><id>UZ</id><![CDATA[Ozbekistan]]><value/></item><item><id>PK</id><![CDATA[Pakistan]]><value/></item><item><id>PW</id><![CDATA[Palao]]><value/></item><item><id>PS</id><![CDATA[Palestina]]><value/></item><item><id>PA</id><![CDATA[Panama]]><value/></item><item><id>PG</id><![CDATA[Papouasie-Nouvelle-Guinée]]><value/></item><item><id>PY</id><![CDATA[Paragoay]]><value/></item><item><id>PE</id><![CDATA[Peroa]]><value/></item><item><id>PN</id><![CDATA[Pitkairn]]><value/></item><item><id>PL</id><![CDATA[Pôlôna]]><value/></item><item><id>PF</id><![CDATA[Polynezia frantsay]]><value/></item><item><id>PT</id><![CDATA[Pôrtiogala]]><value/></item><item><id>PR</id><![CDATA[Pôrtô Rikô]]><value/></item><item><id>DO</id><![CDATA[Repoblika Dominikanina]]><value/></item><item><id>CF</id><![CDATA[Repoblika Ivon’Afrika]]><value/></item><item><id>CD</id><![CDATA[Repoblikan’i Kongo]]><value/></item><item><id>CZ</id><![CDATA[Repoblikan’i Tseky]]><value/></item><item><id>RW</id><![CDATA[Roanda]]><value/></item><item><id>RO</id><![CDATA[Romania]]><value/></item><item><id>RU</id><![CDATA[Rosia]]><value/></item><item><id>KN</id><![CDATA[Saint-Christophe-et-Niévès]]><value/></item><item><id>SM</id><![CDATA[Saint-Marin]]><value/></item><item><id>PM</id><![CDATA[Saint-Pierre-et-Miquelon]]><value/></item><item><id>VC</id><![CDATA[Saint-Vincent-et-les Grenadines]]><value/></item><item><id>SH</id><![CDATA[Sainte-Hélène]]><value/></item><item><id>LC</id><![CDATA[Sainte-Lucie]]><value/></item><item><id>WS</id><![CDATA[Samoa]]><value/></item><item><id>AS</id><![CDATA[Samoa amerikanina]]><value/></item><item><id>ST</id><![CDATA[São Tomé-et-Príncipe]]><value/></item><item><id>SN</id><![CDATA[Senegal]]><value/></item><item><id>RS</id><![CDATA[Serbia]]><value/></item><item><id>SC</id><![CDATA[Seyshela]]><value/></item><item><id>CL</id><![CDATA[Shili]]><value/></item><item><id>SL</id><![CDATA[Sierra Leone]]><value/></item><item><id>CN</id><![CDATA[Sina]]><value/></item><item><id>SG</id><![CDATA[Singaporo]]><value/></item><item><id>SX</id><![CDATA[Sint Maarten]]><value/></item><item><id>SK</id><![CDATA[Slovakia]]><value/></item><item><id>SI</id><![CDATA[Slovenia]]><value/></item><item><id>SZ</id><![CDATA[Soazilandy]]><value/></item><item><id>SD</id><![CDATA[Sodan]]><value/></item><item><id>SE</id><![CDATA[Soedy]]><value/></item><item><id>CH</id><![CDATA[Soisa]]><value/></item><item><id>SO</id><![CDATA[Somalia]]><value/></item><item><id>SR</id><![CDATA[Sorinam]]><value/></item><item><id>GS</id><![CDATA[South Georgia & South Sandwich Islands]]><value/></item><item><id>SS</id><![CDATA[South Sudan]]><value/></item><item><id>LK</id><![CDATA[Sri Lanka]]><value/></item><item><id>BL</id><![CDATA[St. Barthélemy]]><value/></item><item><id>MF</id><![CDATA[St. Martin]]><value/></item><item><id>SJ</id><![CDATA[Svalbard & Jan Mayen]]><value/></item><item><id>CY</id><![CDATA[Sypra]]><value/></item><item><id>SY</id><![CDATA[Syria]]><value/></item><item><id>TW</id><![CDATA[Taioana]]><value/></item><item><id>TJ</id><![CDATA[Tajikistan]]><value/></item><item><id>TZ</id><![CDATA[Tanzania]]><value/></item><item><id>TH</id><![CDATA[Thailandy]]><value/></item><item><id>TL</id><![CDATA[Timor Atsinanana]]><value/></item><item><id>TG</id><![CDATA[Togo]]><value/></item><item><id>TK</id><![CDATA[Tokelao]]><value/></item><item><id>TO</id><![CDATA[Tongà]]><value/></item><item><id>TN</id><![CDATA[Tonizia]]><value/></item><item><id>TR</id><![CDATA[Torkia]]><value/></item><item><id>TM</id><![CDATA[Torkmenistan]]><value/></item><item><id>TV</id><![CDATA[Tovalò]]><value/></item><item><id>TT</id><![CDATA[Trinidad sy Tobagô]]><value/></item><item><id>TA</id><![CDATA[Tristan da Cunha]]><value/></item><item><id>TD</id><![CDATA[Tsady]]><value/></item><item><id>UM</id><![CDATA[U.S. Outlying Islands]]><value/></item><item><id>VU</id><![CDATA[Vanoatò]]><value/></item><item><id>VE</id><![CDATA[Venezoelà]]><value/></item><item><id>VN</id><![CDATA[Vietnam]]><value/></item><item><id>WF</id><![CDATA[Wallis sy Futuna]]><value/></item><item><id>EH</id><![CDATA[Western Sahara]]><value/></item><item><id>YE</id><![CDATA[Yemen]]><value/></item><item><id>ZM</id><![CDATA[Zambia]]><value/></item><item><id>GE</id><![CDATA[Zeorzia]]><value/></item><item><id>GI</id><![CDATA[Zibraltara]]><value/></item><item><id>ZW</id><![CDATA[Zimbaboe]]><value/></item></values>
