<?xml version="1.0" encoding="utf-8"?>
<resources xmlns:tools="http://schemas.android.com/tools">
  <string name="COUNTRY_NAME_AF">Afganistan</string>
  <string name="COUNTRY_NAME_ZA">Afrika t’Isfel</string>
  <string name="COUNTRY_NAME_AL">Albanija</string>
  <string name="COUNTRY_NAME_DZ">Alġerija</string>
  <string name="COUNTRY_NAME_AD">Andorra</string>
  <string name="COUNTRY_NAME_AO">Angola</string>
  <string name="COUNTRY_NAME_AI">Angwilla</string>
  <string name="COUNTRY_NAME_AQ">Antartika</string>
  <string name="COUNTRY_NAME_AG">Antigua and Barbuda</string>
  <string name="COUNTRY_NAME_AN">Antilles Olandiżi</string>
  <string name="COUNTRY_NAME_AR">Arġentina</string>
  <string name="COUNTRY_NAME_AM">Armenja</string>
  <string name="COUNTRY_NAME_AW">Aruba</string>
  <string name="COUNTRY_NAME_AU">Awstralja</string>
  <string name="COUNTRY_NAME_AT">Awstrija</string>
  <string name="COUNTRY_NAME_AZ">Ażerbajġan</string>
  <string name="COUNTRY_NAME_BS">Baħamas</string>
  <string name="COUNTRY_NAME_BH">Baħrajn</string>
  <string name="COUNTRY_NAME_BD">Bangladexx</string>
  <string name="COUNTRY_NAME_BB">Barbados</string>
  <string name="COUNTRY_NAME_BE">Belġju</string>
  <string name="COUNTRY_NAME_BZ">Beliże</string>
  <string name="COUNTRY_NAME_BJ">Benin</string>
  <string name="COUNTRY_NAME_BM">Bermuda</string>
  <string name="COUNTRY_NAME_BY">Bjelorussja</string>
  <string name="COUNTRY_NAME_BO">Bolivja</string>
  <string name="COUNTRY_NAME_BW">Botswana</string>
  <string name="COUNTRY_NAME_BV">Bouvet Island</string>
  <string name="COUNTRY_NAME_BA">Bożnija Ħerżegovina</string>
  <string name="COUNTRY_NAME_BR">Brażil</string>
  <string name="COUNTRY_NAME_IO">British Indian Ocean Territory</string>
  <string name="COUNTRY_NAME_VG">British Virgin Islands</string>
  <string name="COUNTRY_NAME_BN">Brunej</string>
  <string name="COUNTRY_NAME_BG">Bulgarija</string>
  <string name="COUNTRY_NAME_BF">Burkina Faso</string>
  <string name="COUNTRY_NAME_BI">Burundi</string>
  <string name="COUNTRY_NAME_BT">Butan</string>
  <string name="COUNTRY_NAME_TD">Ċad</string>
  <string name="COUNTRY_NAME_CL">Ċili</string>
  <string name="COUNTRY_NAME_CN">Ċina</string>
  <string name="COUNTRY_NAME_CY">Ċipru</string>
  <string name="COUNTRY_NAME_CX">Christmas Island</string>
  <string name="COUNTRY_NAME_CC">Cocos (Keeling) Islands</string>
  <string name="COUNTRY_NAME_CK">Cook Islands</string>
  <string name="COUNTRY_NAME_DK">Danimarka</string>
  <string name="COUNTRY_NAME_CD">Democratic Republic of the Congo</string>
  <string name="COUNTRY_NAME_DM">Dominika</string>
  <string name="COUNTRY_NAME_EG">Eġittu</string>
  <string name="COUNTRY_NAME_EC">Ekwador</string>
  <string name="COUNTRY_NAME_SV">El Salvador</string>
  <string name="COUNTRY_NAME_AE">Emirati Għarab Maqgħuda</string>
  <string name="COUNTRY_NAME_ER">Eritreja</string>
  <string name="COUNTRY_NAME_EE">Estonja</string>
  <string name="COUNTRY_NAME_ET">Etijopja</string>
  <string name="COUNTRY_NAME_FK">Falkland Islands</string>
  <string name="COUNTRY_NAME_FJ">Fiġi</string>
  <string name="COUNTRY_NAME_PH">Filippini</string>
  <string name="COUNTRY_NAME_FI">Finlandja</string>
  <string name="COUNTRY_NAME_FR">Franza</string>
  <string name="COUNTRY_NAME_JM">Ġamajka</string>
  <string name="COUNTRY_NAME_JP">Ġappun</string>
  <string name="COUNTRY_NAME_DE">Ġermanja</string>
  <string name="COUNTRY_NAME_DJ">Ġibuti</string>
  <string name="COUNTRY_NAME_JO">Ġordan</string>
  <string name="COUNTRY_NAME_GE">Ġorġja</string>
  <string name="COUNTRY_NAME_GA">Gabon</string>
  <string name="COUNTRY_NAME_GM">Gambja</string>
  <string name="COUNTRY_NAME_GH">Gana</string>
  <string name="COUNTRY_NAME_GI">Gibraltar</string>
  <string name="COUNTRY_NAME_GQ">Ginea Ekwatorjali</string>
  <string name="COUNTRY_NAME_GW">Ginea-Bissaw</string>
  <string name="COUNTRY_NAME_GN">Gineja</string>
  <string name="COUNTRY_NAME_GR">Greċja</string>
  <string name="COUNTRY_NAME_GD">Grenada</string>
  <string name="COUNTRY_NAME_GL">Grinlandja</string>
  <string name="COUNTRY_NAME_GY">Gujana</string>
  <string name="COUNTRY_NAME_GF">Gujana Franċiża</string>
  <string name="COUNTRY_NAME_GP">Gwadelupe</string>
  <string name="COUNTRY_NAME_GU">Gwam</string>
  <string name="COUNTRY_NAME_GT">Gwatemala</string>
  <string name="COUNTRY_NAME_AX">Gżejjer Aland</string>
  <string name="COUNTRY_NAME_FO">Gżejjer Faroe</string>
  <string name="COUNTRY_NAME_KY">Gżejjer Kajmani</string>
  <string name="COUNTRY_NAME_MP">Gżejjer Marjana ta’ Fuq</string>
  <string name="COUNTRY_NAME_MH">Gżejjer ta’ Marshall</string>
  <string name="COUNTRY_NAME_SA">Għarabja Sawdita</string>
  <string name="COUNTRY_NAME_HM">Heard Island and McDonald Islands</string>
  <string name="COUNTRY_NAME_HT">Ħaiti</string>
  <string name="COUNTRY_NAME_HN">Ħonduras</string>
  <string name="COUNTRY_NAME_HK">Ħong Kong S.A.R., Ċina</string>
  <string name="COUNTRY_NAME_IN">Indja</string>
  <string name="COUNTRY_NAME_ID">Indoneżja</string>
  <string name="COUNTRY_NAME_GB">Ingilterra</string>
  <string name="COUNTRY_NAME_IR">Iran</string>
  <string name="COUNTRY_NAME_IQ">Iraq</string>
  <string name="COUNTRY_NAME_IE">Irlanda</string>
  <string name="COUNTRY_NAME_IS">Islanda</string>
  <string name="COUNTRY_NAME_IM">Isle of Man</string>
  <string name="COUNTRY_NAME_IT">Italja</string>
  <string name="COUNTRY_NAME_IL">Iżrael</string>
  <string name="COUNTRY_NAME_YE">Jemen</string>
  <string name="COUNTRY_NAME_KH">Kambodja</string>
  <string name="COUNTRY_NAME_CM">Kamerun</string>
  <string name="COUNTRY_NAME_CA">Kanada</string>
  <string name="COUNTRY_NAME_CV">Kape Verde</string>
  <string name="COUNTRY_NAME_KZ">Każakstan</string>
  <string name="COUNTRY_NAME_KE">Kenja</string>
  <string name="COUNTRY_NAME_KG">Kirgistan</string>
  <string name="COUNTRY_NAME_KI">Kiribati</string>
  <string name="COUNTRY_NAME_CO">Kolumbja</string>
  <string name="COUNTRY_NAME_KM">Komoros</string>
  <string name="COUNTRY_NAME_CG">Kongo</string>
  <string name="COUNTRY_NAME_KR">Koreja t’Isfel</string>
  <string name="COUNTRY_NAME_KP">Koreja ta’ Fuq</string>
  <string name="COUNTRY_NAME_CR">Kosta Rika</string>
  <string name="COUNTRY_NAME_CI">Kosta ta’ l-Avorju</string>
  <string name="COUNTRY_NAME_HR">Kroazja</string>
  <string name="COUNTRY_NAME_CU">Kuba</string>
  <string name="COUNTRY_NAME_KW">Kuwajt</string>
  <string name="COUNTRY_NAME_LA">Laos</string>
  <string name="COUNTRY_NAME_LV">Latvja</string>
  <string name="COUNTRY_NAME_LS">Lesoto</string>
  <string name="COUNTRY_NAME_LB">Libanu</string>
  <string name="COUNTRY_NAME_LR">Liberja</string>
  <string name="COUNTRY_NAME_LY">Libja</string>
  <string name="COUNTRY_NAME_LI">Liechtenstein</string>
  <string name="COUNTRY_NAME_LT">Litwanja</string>
  <string name="COUNTRY_NAME_LU">Lussemburgu</string>
  <string name="COUNTRY_NAME_MK">Maċedonja</string>
  <string name="COUNTRY_NAME_MO">Macao S.A.R., China</string>
  <string name="COUNTRY_NAME_MG">Madagaskar</string>
  <string name="COUNTRY_NAME_YT">Majotte</string>
  <string name="COUNTRY_NAME_MY">Malasja</string>
  <string name="COUNTRY_NAME_MW">Malawi</string>
  <string name="COUNTRY_NAME_MV">Maldives</string>
  <string name="COUNTRY_NAME_MD">Maldova</string>
  <string name="COUNTRY_NAME_ML">Mali</string>
  <string name="COUNTRY_NAME_MT">Malta</string>
  <string name="COUNTRY_NAME_MA">Marokk</string>
  <string name="COUNTRY_NAME_MQ">Martinik</string>
  <string name="COUNTRY_NAME_MR">Mawritanja</string>
  <string name="COUNTRY_NAME_MU">Mawrizju</string>
  <string name="COUNTRY_NAME_MX">Messiku</string>
  <string name="COUNTRY_NAME_FM">Mikronesja</string>
  <string name="COUNTRY_NAME_MM">Mjanmar</string>
  <string name="COUNTRY_NAME_MC">Monako</string>
  <string name="COUNTRY_NAME_MN">Mongolja</string>
  <string name="COUNTRY_NAME_MS">Montserrat</string>
  <string name="COUNTRY_NAME_MZ">Możambik</string>
  <string name="COUNTRY_NAME_NA">Namibja</string>
  <string name="COUNTRY_NAME_NR">Nauru</string>
  <string name="COUNTRY_NAME_NP">Nepal</string>
  <string name="COUNTRY_NAME_NC">New Caledonia</string>
  <string name="COUNTRY_NAME_NZ">New Zealand</string>
  <string name="COUNTRY_NAME_NE">Niġer</string>
  <string name="COUNTRY_NAME_NG">Niġerja</string>
  <string name="COUNTRY_NAME_NI">Nikaragwa</string>
  <string name="COUNTRY_NAME_NU">Niue</string>
  <string name="COUNTRY_NAME_NF">Norfolk Island</string>
  <string name="COUNTRY_NAME_NO">Norveġja</string>
  <string name="COUNTRY_NAME_NL">Olanda</string>
  <string name="COUNTRY_NAME_OM">Oman</string>
  <string name="COUNTRY_NAME_PK">Pakistan</string>
  <string name="COUNTRY_NAME_PW">Palau</string>
  <string name="COUNTRY_NAME_PS">Palestinian Territory</string>
  <string name="COUNTRY_NAME_PA">Panama</string>
  <string name="COUNTRY_NAME_PG">Papwa-Ginea Ġdida</string>
  <string name="COUNTRY_NAME_PY">Paragwaj</string>
  <string name="COUNTRY_NAME_PE">Peru</string>
  <string name="COUNTRY_NAME_PN">Pitcairn</string>
  <string name="COUNTRY_NAME_PF">Polinesja Franċiża</string>
  <string name="COUNTRY_NAME_PL">Polonja</string>
  <string name="COUNTRY_NAME_PT">Portugall</string>
  <string name="COUNTRY_NAME_PR">Puerto Rico</string>
  <string name="COUNTRY_NAME_QA">Qatar</string>
  <string name="COUNTRY_NAME_CF">Repubblika Afrikana Ċentrali</string>
  <string name="COUNTRY_NAME_CZ">Repubblika Ċeka</string>
  <string name="COUNTRY_NAME_DO">Republikka Domenikana</string>
  <string name="COUNTRY_NAME_RE">Réunion</string>
  <string name="COUNTRY_NAME_RO">Rumanija</string>
  <string name="COUNTRY_NAME_RU">Russja</string>
  <string name="COUNTRY_NAME_RW">Rwanda</string>
  <string name="COUNTRY_NAME_EH">Sahara tal-Punent</string>
  <string name="COUNTRY_NAME_SH">Saint Helena</string>
  <string name="COUNTRY_NAME_KN">Saint Kitts and Nevis</string>
  <string name="COUNTRY_NAME_PM">Saint Pierre and Miquelon</string>
  <string name="COUNTRY_NAME_VC">Saint Vincent and the Grenadines</string>
  <string name="COUNTRY_NAME_WS">Samoa</string>
  <string name="COUNTRY_NAME_AS">Samoa Amerikana</string>
  <string name="COUNTRY_NAME_SM">San Marino</string>
  <string name="COUNTRY_NAME_LC">Santa Luċija</string>
  <string name="COUNTRY_NAME_ST">Sao Tome and Principe</string>
  <string name="COUNTRY_NAME_SN">Senegal</string>
  <string name="COUNTRY_NAME_CS">Serbja u Montenegro</string>
  <string name="COUNTRY_NAME_SC">Seychelles</string>
  <string name="COUNTRY_NAME_SL">Sierra Leone</string>
  <string name="COUNTRY_NAME_SG">Singapor</string>
  <string name="COUNTRY_NAME_SY">Sirja</string>
  <string name="COUNTRY_NAME_SK">Slovakkja</string>
  <string name="COUNTRY_NAME_SI">Slovenja</string>
  <string name="COUNTRY_NAME_SB">Solomon Islands</string>
  <string name="COUNTRY_NAME_SO">Somalja</string>
  <string name="COUNTRY_NAME_GS">South Georgia and the South Sandwich Islands</string>
  <string name="COUNTRY_NAME_ES">Spanja</string>
  <string name="COUNTRY_NAME_LK">Sri Lanka</string>
  <string name="COUNTRY_NAME_US">Stati Uniti</string>
  <string name="COUNTRY_NAME_SD">Sudan</string>
  <string name="COUNTRY_NAME_SR">Surinam</string>
  <string name="COUNTRY_NAME_SJ">Svalbard and Jan Mayen</string>
  <string name="COUNTRY_NAME_CH">Svizzera</string>
  <string name="COUNTRY_NAME_SZ">Sważiland</string>
  <string name="COUNTRY_NAME_TJ">Taġikistan</string>
  <string name="COUNTRY_NAME_TH">Tajlandja</string>
  <string name="COUNTRY_NAME_TW">Tajwan</string>
  <string name="COUNTRY_NAME_TZ">Tanżanija</string>
  <string name="COUNTRY_NAME_TF">Territorji Franċiżi ta’ Nofsinhar</string>
  <string name="COUNTRY_NAME_TL">Timor tal-Lvant</string>
  <string name="COUNTRY_NAME_TG">Togo</string>
  <string name="COUNTRY_NAME_TK">Tokelaw</string>
  <string name="COUNTRY_NAME_TO">Tonga</string>
  <string name="COUNTRY_NAME_TT">Trinidad u Tobago</string>
  <string name="COUNTRY_NAME_TN">Tuneż</string>
  <string name="COUNTRY_NAME_TR">Turkija</string>
  <string name="COUNTRY_NAME_TM">Turkmenistan</string>
  <string name="COUNTRY_NAME_TC">Turks and Caicos Islands</string>
  <string name="COUNTRY_NAME_TV">Tuvalu</string>
  <string name="COUNTRY_NAME_VI">U.S. Virgin Islands</string>
  <string name="COUNTRY_NAME_UG">Uganda</string>
  <string name="COUNTRY_NAME_UA">Ukraina</string>
  <string name="COUNTRY_NAME_HU">Ungerija</string>
  <string name="COUNTRY_NAME_UM">United States Minor Outlying Islands</string>
  <string name="COUNTRY_NAME_EU">Unjoni Ewropea</string>
  <string name="COUNTRY_NAME_UY">Urugwaj</string>
  <string name="COUNTRY_NAME_UZ">Użbekistan</string>
  <string name="COUNTRY_NAME_VU">Vanwatu</string>
  <string name="COUNTRY_NAME_VA">Vatikan</string>
  <string name="COUNTRY_NAME_VE">Venezwela</string>
  <string name="COUNTRY_NAME_VN">Vjetnam</string>
  <string name="COUNTRY_NAME_WF">Wallis and Futuna</string>
  <string name="COUNTRY_NAME_ZM">Żambja</string>
  <string name="COUNTRY_NAME_ZW">Żimbabwe</string>
  <string name="COUNTRY_NAME_SE">Żvezja</string>
</resources>
